germanki/.streamlit/config.toml
germanki/__init__.py
germanki/__main__.py
germanki/anki_connect.py
germanki/app.py
germanki/chatgpt.py
germanki/config.py
germanki/core.py
germanki/photos/__init__.py
germanki/photos/exceptions.py
germanki/photos/pexels.py
germanki/photos/unsplash.py
germanki/save.pkl
germanki/static/audio/.gitignore
germanki/static/audio/__init__.py
germanki/static/audio/sample_Hans.mp3
germanki/static/audio/sample_Marlene.mp3
germanki/static/audio/sample_Vicki.mp3
germanki/static/image/.gitignore
germanki/static/image/__init__.py
germanki/static/input_examples/__init__.py
germanki/static/input_examples/default.yaml
germanki/tts_mp3.py
germanki/ui.py
germanki/utils.py
germanki-0.3.0.dist-info/METADATA
germanki-0.3.0.dist-info/WHEEL
germanki-0.3.0.dist-info/entry_points.txt
germanki-0.3.0.dist-info/RECORD
