Metadata-Version: 2.3
Name: germanki
Version: 0.3.0
Summary: 
Author: Gabriel R. Pereira
Requires-Python: >=3.9, !=2.7.*, !=3.0.*, !=3.1.*, !=3.2.*, !=3.3.*, !=3.4.*, !=3.5.*, !=3.6.*, !=3.7.*, !=3.8.*, !=3.13.*
Classifier: Programming Language :: Python :: 3
Classifier: Programming Language :: Python :: 3.9
Classifier: Programming Language :: Python :: 3.10
Classifier: Programming Language :: Python :: 3.11
Classifier: Programming Language :: Python :: 3.12
Requires-Dist: openai (>=1.61.0,<2.0.0)
Requires-Dist: pydantic (>=2.10.6,<3.0.0)
Requires-Dist: ratelimit (>=2.2.1,<3.0.0)
Requires-Dist: streamlit (>=1.41.1,<2.0.0)
Requires-Dist: tenacity (>=9.0.0,<10.0.0)
